pysomo/__init__.py
pysomo/export.py
pysomo/figures.py
pysomo/tree.py
pysomo-0.0.6.dist-info/LICENSE
pysomo-0.0.6.dist-info/WHEEL
pysomo-0.0.6.dist-info/METADATA
pysomo-0.0.6.dist-info/RECORD
