Metadata-Version: 2.1
Name: pysomo
Version: 0.0.6
Summary: A small solid modeling library.
Home-page: https://github.com/louiscarl/pysomo
License: MIT
Author: Louis Carl Pepin
Author-email: lcpepin@louiscarl.com
Requires-Python: >=3.7,<4.0
Classifier: License :: OSI Approved :: MIT License
Classifier: Programming Language :: Python :: 3
Classifier: Programming Language :: Python :: 3.7
Classifier: Programming Language :: Python :: 3.8
Classifier: Topic :: Multimedia :: Graphics :: 3D Modeling
Classifier: Topic :: Software Development :: Libraries :: Python Modules
Project-URL: Repository, https://github.com/louiscarl/pysomo
